abslib/__init__.py
abslib/kp.py
abslib-1.0.5.dist-info/LICENSE
abslib-1.0.5.dist-info/METADATA
abslib-1.0.5.dist-info/WHEEL
abslib-1.0.5.dist-info/top_level.txt
abslib-1.0.5.dist-info/RECORD
